trulens/dashboard/__init__.py
trulens/dashboard/appui.py
trulens/dashboard/components/__init__.py
trulens/dashboard/components/record_viewer/__init__.py
trulens/dashboard/components/record_viewer/dist/assets/SourceCodePro-Bold-839f42df.ttf
trulens/dashboard/components/record_viewer/dist/assets/SourceCodePro-Regular-6e5dd049.ttf
trulens/dashboard/components/record_viewer/dist/assets/SourceCodePro-SemiBold-ccfba566.ttf
trulens/dashboard/components/record_viewer/dist/assets/index-00b8e16d.css
trulens/dashboard/components/record_viewer/dist/assets/index-8729bc31.js
trulens/dashboard/components/record_viewer/dist/index.html
trulens/dashboard/components/record_viewer_otel/__init__.py
trulens/dashboard/components/record_viewer_otel/dist/assets/SourceCodePro-Bold-C5Vtz9WP.ttf
trulens/dashboard/components/record_viewer_otel/dist/assets/SourceCodePro-Regular-BoGDH3YB.ttf
trulens/dashboard/components/record_viewer_otel/dist/assets/SourceCodePro-SemiBold-R6YWw784.ttf
trulens/dashboard/components/record_viewer_otel/dist/assets/index-DT9k41iQ.css
trulens/dashboard/components/record_viewer_otel/dist/assets/index-SDsBbLPe.js
trulens/dashboard/components/record_viewer_otel/dist/index.html
trulens/dashboard/constants.py
trulens/dashboard/display.py
trulens/dashboard/main.py
trulens/dashboard/py.typed
trulens/dashboard/run.py
trulens/dashboard/streamlit.py
trulens/dashboard/tabs/Compare.py
trulens/dashboard/tabs/Leaderboard.py
trulens/dashboard/tabs/Records.py
trulens/dashboard/tabs/__init__.py
trulens/dashboard/utils/__init__.py
trulens/dashboard/utils/dashboard_utils.py
trulens/dashboard/utils/metadata_utils.py
trulens/dashboard/utils/notebook_utils.py
trulens/dashboard/utils/records_utils.py
trulens/dashboard/utils/sis_utils.py
trulens/dashboard/utils/streamlit_compat.py
trulens/dashboard/ux/__init__.py
trulens/dashboard/ux/components.py
trulens/dashboard/ux/squid_black.png
trulens/dashboard/ux/styles.py
trulens/dashboard/ux/trulens_logo.svg
trulens/dashboard/ux/trulens_squid.svg
trulens_dashboard-2.5.3.dist-info/METADATA
trulens_dashboard-2.5.3.dist-info/WHEEL
trulens_dashboard-2.5.3.dist-info/RECORD
